{"id":"F7pXcmPnWkLEHkvQBb3zXkgdiHy14GQcP2RQp","title":"Aphyr: Posts","displayTitle":"Dev - Aphyr","url":"http://aphyr.com/posts.atom","feedLink":"http://aphyr.com/posts.atom","isQuery":false,"isEmpty":false,"isHidden":false,"itemCount":1,"items":[{"title":"No, You Can't (Officially) Reconnect Cut Pieces of Hue Strip Lights","url":"https://aphyr.com/posts/402-no-you-cant-officially-reconnect-cut-pieces-of-hue-strip-lights","date":1767374815,"author":"Aphyr","guid":517,"unread":true,"content":"<p>Hopefully this saves someone else an hour of digging. Philips Hue has a <a href=\"https://www.philips-hue.com/en-us/products/smart-light-strips/indoor-led-strip-lights\">comparison page</a> for their strip lights. This table says that for the <a href=\"https://www.philips-hue.com/en-us/p/hue-white-and-color-ambiance-gradient-lightstrip-80-inch/046677570552\">Ambiance Gradient</a> lightstrips, “Cut pieces can be reconnected”. Their <a href=\"https://www.philips-hue.com/en-us/products/smart-light-strips/can-you-cut-led-light-strips\">“Can you cut LED strip lights” page</a> also says “Many strip lights are cuttable, and some even allow the cut parts to be reused and added to the strip light using a connector. Lightstrip V4 and many of the latest models will enable this level of customization.”</p><p>Lightstrip V4 has been out for six years, but at least as far as Hue’s official product line goes, the statement “Cut pieces can be reconnected” is not true. Hue’s support representative told me that Hue might someday release a connector which allows reconnecting cut pieces. However, that product does not exist yet, and they can’t say when it might be released.</p><p>In the meantime, there’s a company called <a href=\"https://www.litcessory.com/collections/philips-hue\">Litcessory</a> which makes third-party adapters for Hue strips. I haven’t tried them, but I think they might do the trick.</p>","contentLength":1019,"flags":null,"enclosureUrl":"","enclosureMime":"","commentsUrl":null}],"tags":["dev"]}